{"nodes": [{"id": "engine_index_barrel", "label": "Engine Public API Barrel", "file_type": "code", "source_file": "server/src/engine/index.ts", "source_location": null, "source_url": null, "captured_at": null, "author": null, "contributor": null}], "edges": [{"source": "engine_index_barrel", "target": "engine_connectormapper_mapconnectors", "relation": "references", "confidence": "EXTRACTED", "confidence_score": 1.0, "source_file": "server/src/engine/index.ts", "source_location": null, "weight": 1.0}, {"source": "engine_index_barrel", "target": "engine_kpiextractor_extractkpis", "relation": "references", "confidence": "EXTRACTED", "confidence_score": 1.0, "source_file": "server/src/engine/index.ts", "source_location": null, "weight": 1.0}, {"source": "engine_index_barrel", "target": "engine_anomalydetector_detectanomalies", "relation": "references", "confidence": "EXTRACTED", "confidence_score": 1.0, "source_file": "server/src/engine/index.ts", "source_location": null, "weight": 1.0}, {"source": "engine_index_barrel", "target": "engine_ask_answerquestion", "relation": "references", "confidence": "EXTRACTED", "confidence_score": 1.0, "source_file": "server/src/engine/index.ts", "source_location": null, "weight": 1.0}, {"source": "engine_index_barrel", "target": "engine_events_ingestevents", "relation": "references", "confidence": "EXTRACTED", "confidence_score": 1.0, "source_file": "server/src/engine/index.ts", "source_location": null, "weight": 1.0}, {"source": "engine_index_barrel", "target": "engine_events_missionevents", "relation": "references", "confidence": "EXTRACTED", "confidence_score": 1.0, "source_file": "server/src/engine/index.ts", "source_location": null, "weight": 1.0}], "hyperedges": []}